toegen/__init__.py
toegen/homology.py
toegen/switch_generator.py
toegen-0.1.0.dist-info/LICENSE.md
toegen-0.1.0.dist-info/METADATA
toegen-0.1.0.dist-info/WHEEL
toegen-0.1.0.dist-info/top_level.txt
toegen-0.1.0.dist-info/RECORD
