Metadata-Version: 2.1
Name: toegen
Version: 0.1.0
Summary: A package for generating toehold switches with homology ranking for gene expression control
Home-page: https://github.com/Orezbm/toegen
Author: Orezbm
Author-email: igemtau2024@gmail.com
Classifier: Programming Language :: Python :: 3
Classifier: License :: OSI Approved :: MIT License
Classifier: Operating System :: OS Independent
Requires-Python: >=3.6
License-File: LICENSE.md
Requires-Dist: biopython
Requires-Dist: pandas
Requires-Dist: joblib
Requires-Dist: fuzzysearch
Requires-Dist: viennarna
